xml2pdf/__init__.py
xml2pdf/cleaner.py
xml2pdf/converter.py
xml2pdf/downloader.py
xml2pdf/xslt_generator.py
xml2pdf-0.2.1.dist-info/LICENSE
xml2pdf-0.2.1.dist-info/METADATA
xml2pdf-0.2.1.dist-info/WHEEL
xml2pdf-0.2.1.dist-info/top_level.txt
xml2pdf-0.2.1.dist-info/RECORD
