Metadata-Version: 2.2
Name: xml2pdf
Version: 0.2.1
Summary: A tool to convert XML files to PDF
Home-page: https://github.com/Higgy-debug/xml2pdf
Author: Hirthickkesh
Author-email: hirthickkeshpr@gmail.com
Classifier: Programming Language :: Python :: 3
Classifier: License :: OSI Approved :: MIT License
Classifier: Operating System :: OS Independent
Requires-Python: >=3.6
License-File: LICENSE
Requires-Dist: requests
Requires-Dist: lxml
Requires-Dist: weasyprint
Dynamic: author
Dynamic: author-email
Dynamic: classifier
Dynamic: description
Dynamic: description-content-type
Dynamic: home-page
Dynamic: requires-dist
Dynamic: requires-python
Dynamic: summary
